image_comparer/__init__.py
image_comparer/cli.py
image_comparer/compare.py
image_comparer/download.py
image_comparer/model.py
image_comparer-1.1.3.dist-info/DESCRIPTION.rst
image_comparer-1.1.3.dist-info/METADATA
image_comparer-1.1.3.dist-info/RECORD
image_comparer-1.1.3.dist-info/WHEEL
image_comparer-1.1.3.dist-info/entry_points.txt
image_comparer-1.1.3.dist-info/metadata.json
image_comparer-1.1.3.dist-info/top_level.txt
