Metadata-Version: 2.0
Name: image-comparer
Version: 1.1.3
Summary: Compares two images using siamese networks
Home-page: https://github.com/joeyism/py-image-comparer
Author: joeyism
License: UNKNOWN
Download-URL: https://github.com/joeyism/py-image-comparer/archive/1.1.3.tar.gz
Keywords: pytorch,torch,machine,learning,image,compare,comparer,siamese,network,networks
Platform: UNKNOWN
Requires-Dist: numpy (>=1.16.1)
Requires-Dist: Pillow (==5.4.1)
Requires-Dist: torch (>=1.0.1.post2)
Requires-Dist: torchvision (==0.2.1)
Requires-Dist: opencv-python (==4.5.2.54)
Requires-Dist: tqdm (==4.61.2)
Requires-Dist: requests (==2.25.1)
